sql-format/__init__.py
sql-format/__main__.py
sql_format/__init__.py
sql_format/__main__.py
sql_format-0.1.0.dist-info/LICENSE
sql_format-0.1.0.dist-info/METADATA
sql_format-0.1.0.dist-info/WHEEL
sql_format-0.1.0.dist-info/entry_points.txt
sql_format-0.1.0.dist-info/top_level.txt
sql_format-0.1.0.dist-info/RECORD
