Metadata-Version: 2.1
Name: sql-format
Version: 0.1.0
Summary: Format your SQL statements using the sql-pretty-printer API
Home-page: https://github.com/rrickgauer/sql-format
Author: Ryan Rickgauer
Author-email: rrickgauer1@gmail.com
License: UNKNOWN
Platform: UNKNOWN
Classifier: Programming Language :: Python :: 3
Classifier: License :: OSI Approved :: MIT License
Classifier: Operating System :: OS Independent
Requires-Python: >=3.6
